termdeployr_llmdeploy_stepdeploy_cliassist_deployflow_termguide_llmdeployer_deploymate_terminaldeploy_smartdeploy/__init__.py
termdeployr_llmdeploy_stepdeploy_cliassist_deployflow_termguide_llmdeployer_deploymate_terminaldeploy_smartdeploy/main.py
termdeployr_llmdeploy_stepdeploy_cliassist_deployflow_termguide_llmdeployer_deploymate_terminaldeploy_smartdeploy/prompts.py
termdeployr_llmdeploy_stepdeploy_cliassist_deployflow_termguide_llmdeployer_deploymate_terminaldeploy_smartdeploy-2025.12.21142331.dist-info/METADATA
termdeployr_llmdeploy_stepdeploy_cliassist_deployflow_termguide_llmdeployer_deploymate_terminaldeploy_smartdeploy-2025.12.21142331.dist-info/WHEEL
termdeployr_llmdeploy_stepdeploy_cliassist_deployflow_termguide_llmdeployer_deploymate_terminaldeploy_smartdeploy-2025.12.21142331.dist-info/top_level.txt
termdeployr_llmdeploy_stepdeploy_cliassist_deployflow_termguide_llmdeployer_deploymate_terminaldeploy_smartdeploy-2025.12.21142331.dist-info/RECORD
