Metadata-Version: 2.4
Name: termdeployr-llmdeploy-stepdeploy-cliassist-deployflow-termguide-llmdeployer-deploymate-terminaldeploy-smartdeploy
Version: 2025.12.21142331
Summary: A new package that helps users deploy applications by providing structured, step-by-step guidance through terminal commands. Users input their deployment goals or issues, and the package uses llmatch-
Author-email: termdeployr-llmdeploy-stepdeploy-cliassist-deployflow-termguide-llmdeployer-deploymate-terminaldeploy-smartdeploy <hi@eugene.plus>
License: MIT
Project-URL: Homepage, https://github.com/chigwell
Requires-Python: >=3.9
Requires-Dist: langchain-llm7>=0.0.0
Requires-Dist: llmatch-messages>=0.0.0
Requires-Dist: langchain-core>=0.3.0
